{
  "warrior": {
    "items": [
      "treasures/warrior/belt",
      "treasures/warrior/sword",
      "treasures/warrior/shield",
      "treasures/warrior/crown",
      "treasures/warrior/cloak",
      "treasures/warrior/armor"
    ],
    "missing": "treasures/warrior/shield"
  },
  "hero": {
    "items": [
      "treasures/hero/spear",
      "treasures/hero/cape_armor",
      "treasures/hero/helmet",
      "treasures/hero/necklace",
      "treasures/hero/garment",
      "treasures/hero/armor"
    ],
    "missing": "treasures/hero/necklace"
  },
  "creature": {
    "items": [
      "treasures/creature/spear",
      "treasures/creature/horns",
      "treasures/creature/wings",
      "treasures/creature/venom",
      "treasures/creature/wings_2",
      "treasures/creature/head"
    ],
    "missing": "treasures/creature/wings_2"
  },
  "titan": {
    "items": [
      "treasures/titan/crown",
      "treasures/titan/maul",
      "treasures/titan/sphere",
      "treasures/titan/garment",
      "treasures/titan/staff",
      "treasures/titan/wings"
    ],
    "missing": "treasures/titan/staff"
  },
  "god": {
    "items": [
      "treasures/god/arrows",
      "treasures/god/tiara",
      "treasures/god/garment",
      "treasures/god/armor",
      "treasures/god/trident",
      "treasures/god/ring"
    ],
    "missing": "treasures/god/tiara"
  }
}
